aliyunsdkhbr/__init__.py
aliyunsdkhbr/endpoint.py
aliyunsdkhbr/request/__init__.py
aliyunsdkhbr/request/v20170908/AddContainerClusterRequest.py
aliyunsdkhbr/request/v20170908/CancelBackupJobRequest.py
aliyunsdkhbr/request/v20170908/CancelRestoreJobRequest.py
aliyunsdkhbr/request/v20170908/ChangeResourceGroupRequest.py
aliyunsdkhbr/request/v20170908/CheckRoleRequest.py
aliyunsdkhbr/request/v20170908/CreateBackupJobRequest.py
aliyunsdkhbr/request/v20170908/CreateBackupPlanRequest.py
aliyunsdkhbr/request/v20170908/CreateClientsRequest.py
aliyunsdkhbr/request/v20170908/CreateHanaBackupPlanRequest.py
aliyunsdkhbr/request/v20170908/CreateHanaInstanceRequest.py
aliyunsdkhbr/request/v20170908/CreateHanaRestoreRequest.py
aliyunsdkhbr/request/v20170908/CreatePolicyBindingsRequest.py
aliyunsdkhbr/request/v20170908/CreatePolicyV2Request.py
aliyunsdkhbr/request/v20170908/CreateReplicationVaultRequest.py
aliyunsdkhbr/request/v20170908/CreateRestoreJobRequest.py
aliyunsdkhbr/request/v20170908/CreateTempFileUploadUrlRequest.py
aliyunsdkhbr/request/v20170908/CreateVaultRequest.py
aliyunsdkhbr/request/v20170908/DeleteBackupClientRequest.py
aliyunsdkhbr/request/v20170908/DeleteBackupClientResourceRequest.py
aliyunsdkhbr/request/v20170908/DeleteBackupPlanRequest.py
aliyunsdkhbr/request/v20170908/DeleteClientRequest.py
aliyunsdkhbr/request/v20170908/DeleteHanaBackupPlanRequest.py
aliyunsdkhbr/request/v20170908/DeleteHanaInstanceRequest.py
aliyunsdkhbr/request/v20170908/DeletePolicyBindingRequest.py
aliyunsdkhbr/request/v20170908/DeletePolicyV2Request.py
aliyunsdkhbr/request/v20170908/DeleteSnapshotRequest.py
aliyunsdkhbr/request/v20170908/DeleteUdmDiskRequest.py
aliyunsdkhbr/request/v20170908/DeleteUdmEcsInstanceRequest.py
aliyunsdkhbr/request/v20170908/DeleteVaultRequest.py
aliyunsdkhbr/request/v20170908/DescribeBackupClientsRequest.py
aliyunsdkhbr/request/v20170908/DescribeBackupJobs2Request.py
aliyunsdkhbr/request/v20170908/DescribeBackupPlansRequest.py
aliyun_python_sdk_hbr-1.2.10.dist-info/LICENSE
aliyun_python_sdk_hbr-1.2.10.dist-info/METADATA
aliyun_python_sdk_hbr-1.2.10.dist-info/WHEEL
aliyun_python_sdk_hbr-1.2.10.dist-info/top_level.txt
aliyun_python_sdk_hbr-1.2.10.dist-info/RECORD
